src/compare_4.v
module compare_4(
    input  wire [3:0] a,
    input  wire [3:0] b,
    output wire [2:0] o
);
    assign o = {a > b, a == b, a < b}; 
endmodule

sim/tb_compare_4.sv
`timescale 1ns/1ps
module tb_compare_4;
    reg [3:0] a,b;
    wire [2:0] o;
    compare_4 dut(a,b,o);
    integer n,checked=0;
    reg [2:0] expected;

    initial begin
        $dumpfile("wave.vcd");
        $dumpvars(0,tb_compare_4);
        for(n=0;n<256;n=n+1) begin
            {a,b}=n;
            expected=((n/16)>(n%16)) ? 4 : (((n/16)==(n%16)) ? 2 : 1);
            #10;
            if (o !== expected)
                $fatal(1,"FAIL compare_4 vector=%0d expected=%h actual=%h",n,expected,o);
            checked=checked+1;
        end
        if(checked!=256) $fatal(1,"Incomplete test");
        $display("LAB1_PASS compare_4 cases=%0d",checked);
        $finish;
    end

    initial begin #100000; $fatal(1,"Watchdog"); end
endmodule

evidence/wave.vcd
$date
	Mon Sep 14 03:22:56 2026
$end
$version
	Icarus Verilog
$end
$timescale
	1ps
$end
$scope module tb_compare_4 $end
$var wire 3 ! o [2:0] $end
$var reg 4 " a [3:0] $end
$var reg 4 # b [3:0] $end
$var reg 3 $ expected [2:0] $end
$var integer 32 % checked [31:0] $end
$var integer 32 & n [31:0] $end
$scope module dut $end
$var wire 4 ' a [3:0] $end
$var wire 4 ( b [3:0] $end
$var wire 3 ) o [2:0] $end
$upscope $end
$upscope $end
$enddefinitions $end
$comment Show the parameter values. $end
$dumpall
$end
#0
$dumpvars
b10 )
b0 (
b0 '
b0 &
b0 %
b10 $
b0 #
b0 "
b10 !
$end
#10000
b1 $
b1 !
b1 )
b1 #
b1 (
b1 &
b1 %
#20000
b10 #
b10 (
b10 &
b10 %
#30000
b11 #
b11 (
b11 &
b11 %
#40000
b100 #
b100 (
b100 &
b100 %
#50000
b101 #
b101 (
b101 &
b101 %
#60000
b110 #
b110 (
b110 &
b110 %
#70000
b111 #
b111 (
b111 &
b111 %
#80000
b1000 #
b1000 (
b1000 &
b1000 %
#90000
b1001 #
b1001 (
b1001 &
b1001 %
#100000
b1010 #
b1010 (
b1010 &
b1010 %
#110000
b1011 #
b1011 (
b1011 &
b1011 %
#120000
b1100 #
b1100 (
b1100 &
b1100 %
#130000
b1101 #
b1101 (
b1101 &
b1101 %
#140000
b1110 #
b1110 (
b1110 &
b1110 %
#150000
b1111 #
b1111 (
b1111 &
b1111 %
#160000
b100 $
b1 "
b1 '
b100 !
b100 )
b0 #
b0 (
b10000 &
b10000 %
#170000
b10 $
b10 !
b10 )
b1 #
b1 (
b10001 &
b10001 %
#180000
b1 $
b1 !
b1 )
b10 #
b10 (
b10010 &
b10010 %
#190000
b11 #
b11 (
b10011 &
b10011 %
#200000
b100 #
b100 (
b10100 &
b10100 %
#210000
b101 #
b101 (
b10101 &
b10101 %
#220000
b110 #
b110 (
b10110 &
b10110 %
#230000
b111 #
b111 (
b10111 &
b10111 %
#240000
b1000 #
b1000 (
b11000 &
b11000 %
#250000
b1001 #
b1001 (
b11001 &
b11001 %
#260000
b1010 #
b1010 (
b11010 &
b11010 %
#270000
b1011 #
b1011 (
b11011 &
b11011 %
#280000
b1100 #
b1100 (
b11100 &
b11100 %
#290000
b1101 #
b1101 (
b11101 &
b11101 %
#300000
b1110 #
b1110 (
b11110 &
b11110 %
#310000
b1111 #
b1111 (
b11111 &
b11111 %
#320000
b100 $
b10 "
b10 '
b100 !
b100 )
b0 #
b0 (
b100000 &
b100000 %
#330000
b1 #
b1 (
b100001 &
b100001 %
#340000
b10 $
b10 !
b10 )
b10 #
b10 (
b100010 &
b100010 %
#350000
b1 $
b1 !
b1 )
b11 #
b11 (
b100011 &
b100011 %
#360000
b100 #
b100 (
b100100 &
b100100 %
#370000
b101 #
b101 (
b100101 &
b100101 %
#380000
b110 #
b110 (
b100110 &
b100110 %
#390000
b111 #
b111 (
b100111 &
b100111 %
#400000
b1000 #
b1000 (
b101000 &
b101000 %
#410000
b1001 #
b1001 (
b101001 &
b101001 %
#420000
b1010 #
b1010 (
b101010 &
b101010 %
#430000
b1011 #
b1011 (
b101011 &
b101011 %
#440000
b1100 #
b1100 (
b101100 &
b101100 %
#450000
b1101 #
b1101 (
b101101 &
b101101 %
#460000
b1110 #
b1110 (
b101110 &
b101110 %
#470000
b1111 #
b1111 (
b101111 &
b101111 %
#480000
b100 $
b11 "
b11 '
b100 !
b100 )
b0 #
b0 (
b110000 &
b110000 %
#490000
b1 #
b1 (
b110001 &
b110001 %
#500000
b10 #
b10 (
b110010 &
b110010 %
#510000
b10 $
b10 !
b10 )
b11 #
b11 (
b110011 &
b110011 %
#520000
b1 $
b1 !
b1 )
b100 #
b100 (
b110100 &
b110100 %
#530000
b101 #
b101 (
b110101 &
b110101 %
#540000
b110 #
b110 (
b110110 &
b110110 %
#550000
b111 #
b111 (
b110111 &
b110111 %
#560000
b1000 #
b1000 (
b111000 &
b111000 %
#570000
b1001 #
b1001 (
b111001 &
b111001 %
#580000
b1010 #
b1010 (
b111010 &
b111010 %
#590000
b1011 #
b1011 (
b111011 &
b111011 %
#600000
b1100 #
b1100 (
b111100 &
b111100 %
#610000
b1101 #
b1101 (
b111101 &
b111101 %
#620000
b1110 #
b1110 (
b111110 &
b111110 %
#630000
b1111 #
b1111 (
b111111 &
b111111 %
#640000
b100 $
b100 "
b100 '
b100 !
b100 )
b0 #
b0 (
b1000000 &
b1000000 %
#650000
b1 #
b1 (
b1000001 &
b1000001 %
#660000
b10 #
b10 (
b1000010 &
b1000010 %
#670000
b11 #
b11 (
b1000011 &
b1000011 %
#680000
b10 $
b10 !
b10 )
b100 #
b100 (
b1000100 &
b1000100 %
#690000
b1 $
b1 !
b1 )
b101 #
b101 (
b1000101 &
b1000101 %
#700000
b110 #
b110 (
b1000110 &
b1000110 %
#710000
b111 #
b111 (
b1000111 &
b1000111 %
#720000
b1000 #
b1000 (
b1001000 &
b1001000 %
#730000
b1001 #
b1001 (
b1001001 &
b1001001 %
#740000
b1010 #
b1010 (
b1001010 &
b1001010 %
#750000
b1011 #
b1011 (
b1001011 &
b1001011 %
#760000
b1100 #
b1100 (
b1001100 &
b1001100 %
#770000
b1101 #
b1101 (
b1001101 &
b1001101 %
#780000
b1110 #
b1110 (
b1001110 &
b1001110 %
#790000
b1111 #
b1111 (
b1001111 &
b1001111 %
#800000
b100 $
b101 "
b101 '
b100 !
b100 )
b0 #
b0 (
b1010000 &
b1010000 %
#810000
b1 #
b1 (
b1010001 &
b1010001 %
#820000
b10 #
b10 (
b1010010 &
b1010010 %
#830000
b11 #
b11 (
b1010011 &
b1010011 %
#840000
b100 #
b100 (
b1010100 &
b1010100 %
#850000
b10 $
b10 !
b10 )
b101 #
b101 (
b1010101 &
b1010101 %
#860000
b1 $
b1 !
b1 )
b110 #
b110 (
b1010110 &
b1010110 %
#870000
b111 #
b111 (
b1010111 &
b1010111 %
#880000
b1000 #
b1000 (
b1011000 &
b1011000 %
#890000
b1001 #
b1001 (
b1011001 &
b1011001 %
#900000
b1010 #
b1010 (
b1011010 &
b1011010 %
#910000
b1011 #
b1011 (
b1011011 &
b1011011 %
#920000
b1100 #
b1100 (
b1011100 &
b1011100 %
#930000
b1101 #
b1101 (
b1011101 &
b1011101 %
#940000
b1110 #
b1110 (
b1011110 &
b1011110 %
#950000
b1111 #
b1111 (
b1011111 &
b1011111 %
#960000
b100 $
b110 "
b110 '
b100 !
b100 )
b0 #
b0 (
b1100000 &
b1100000 %
#970000
b1 #
b1 (
b1100001 &
b1100001 %
#980000
b10 #
b10 (
b1100010 &
b1100010 %
#990000
b11 #
b11 (
b1100011 &
b1100011 %
#1000000
b100 #
b100 (
b1100100 &
b1100100 %
#1010000
b101 #
b101 (
b1100101 &
b1100101 %
#1020000
b10 $
b10 !
b10 )
b110 #
b110 (
b1100110 &
b1100110 %
#1030000
b1 $
b1 !
b1 )
b111 #
b111 (
b1100111 &
b1100111 %
#1040000
b1000 #
b1000 (
b1101000 &
b1101000 %
#1050000
b1001 #
b1001 (
b1101001 &
b1101001 %
#1060000
b1010 #
b1010 (
b1101010 &
b1101010 %
#1070000
b1011 #
b1011 (
b1101011 &
b1101011 %
#1080000
b1100 #
b1100 (
b1101100 &
b1101100 %
#1090000
b1101 #
b1101 (
b1101101 &
b1101101 %
#1100000
b1110 #
b1110 (
b1101110 &
b1101110 %
#1110000
b1111 #
b1111 (
b1101111 &
b1101111 %
#1120000
b100 $
b111 "
b111 '
b100 !
b100 )
b0 #
b0 (
b1110000 &
b1110000 %
#1130000
b1 #
b1 (
b1110001 &
b1110001 %
#1140000
b10 #
b10 (
b1110010 &
b1110010 %
#1150000
b11 #
b11 (
b1110011 &
b1110011 %
#1160000
b100 #
b100 (
b1110100 &
b1110100 %
#1170000
b101 #
b101 (
b1110101 &
b1110101 %
#1180000
b110 #
b110 (
b1110110 &
b1110110 %
#1190000
b10 $
b10 !
b10 )
b111 #
b111 (
b1110111 &
b1110111 %
#1200000
b1 $
b1 !
b1 )
b1000 #
b1000 (
b1111000 &
b1111000 %
#1210000
b1001 #
b1001 (
b1111001 &
b1111001 %
#1220000
b1010 #
b1010 (
b1111010 &
b1111010 %
#1230000
b1011 #
b1011 (
b1111011 &
b1111011 %
#1240000
b1100 #
b1100 (
b1111100 &
b1111100 %
#1250000
b1101 #
b1101 (
b1111101 &
b1111101 %
#1260000
b1110 #
b1110 (
b1111110 &
b1111110 %
#1270000
b1111 #
b1111 (
b1111111 &
b1111111 %
#1280000
b100 $
b1000 "
b1000 '
b100 !
b100 )
b0 #
b0 (
b10000000 &
b10000000 %
#1290000
b1 #
b1 (
b10000001 &
b10000001 %
#1300000
b10 #
b10 (
b10000010 &
b10000010 %
#1310000
b11 #
b11 (
b10000011 &
b10000011 %
#1320000
b100 #
b100 (
b10000100 &
b10000100 %
#1330000
b101 #
b101 (
b10000101 &
b10000101 %
#1340000
b110 #
b110 (
b10000110 &
b10000110 %
#1350000
b111 #
b111 (
b10000111 &
b10000111 %
#1360000
b10 $
b10 !
b10 )
b1000 #
b1000 (
b10001000 &
b10001000 %
#1370000
b1 $
b1 !
b1 )
b1001 #
b1001 (
b10001001 &
b10001001 %
#1380000
b1010 #
b1010 (
b10001010 &
b10001010 %
#1390000
b1011 #
b1011 (
b10001011 &
b10001011 %
#1400000
b1100 #
b1100 (
b10001100 &
b10001100 %
#1410000
b1101 #
b1101 (
b10001101 &
b10001101 %
#1420000
b1110 #
b1110 (
b10001110 &
b10001110 %
#1430000
b1111 #
b1111 (
b10001111 &
b10001111 %
#1440000
b100 $
b1001 "
b1001 '
b100 !
b100 )
b0 #
b0 (
b10010000 &
b10010000 %
#1450000
b1 #
b1 (
b10010001 &
b10010001 %
#1460000
b10 #
b10 (
b10010010 &
b10010010 %
#1470000
b11 #
b11 (
b10010011 &
b10010011 %
#1480000
b100 #
b100 (
b10010100 &
b10010100 %
#1490000
b101 #
b101 (
b10010101 &
b10010101 %
#1500000
b110 #
b110 (
b10010110 &
b10010110 %
#1510000
b111 #
b111 (
b10010111 &
b10010111 %
#1520000
b1000 #
b1000 (
b10011000 &
b10011000 %
#1530000
b10 $
b10 !
b10 )
b1001 #
b1001 (
b10011001 &
b10011001 %
#1540000
b1 $
b1 !
b1 )
b1010 #
b1010 (
b10011010 &
b10011010 %
#1550000
b1011 #
b1011 (
b10011011 &
b10011011 %
#1560000
b1100 #
b1100 (
b10011100 &
b10011100 %
#1570000
b1101 #
b1101 (
b10011101 &
b10011101 %
#1580000
b1110 #
b1110 (
b10011110 &
b10011110 %
#1590000
b1111 #
b1111 (
b10011111 &
b10011111 %
#1600000
b100 $
b1010 "
b1010 '
b100 !
b100 )
b0 #
b0 (
b10100000 &
b10100000 %
#1610000
b1 #
b1 (
b10100001 &
b10100001 %
#1620000
b10 #
b10 (
b10100010 &
b10100010 %
#1630000
b11 #
b11 (
b10100011 &
b10100011 %
#1640000
b100 #
b100 (
b10100100 &
b10100100 %
#1650000
b101 #
b101 (
b10100101 &
b10100101 %
#1660000
b110 #
b110 (
b10100110 &
b10100110 %
#1670000
b111 #
b111 (
b10100111 &
b10100111 %
#1680000
b1000 #
b1000 (
b10101000 &
b10101000 %
#1690000
b1001 #
b1001 (
b10101001 &
b10101001 %
#1700000
b10 $
b10 !
b10 )
b1010 #
b1010 (
b10101010 &
b10101010 %
#1710000
b1 $
b1 !
b1 )
b1011 #
b1011 (
b10101011 &
b10101011 %
#1720000
b1100 #
b1100 (
b10101100 &
b10101100 %
#1730000
b1101 #
b1101 (
b10101101 &
b10101101 %
#1740000
b1110 #
b1110 (
b10101110 &
b10101110 %
#1750000
b1111 #
b1111 (
b10101111 &
b10101111 %
#1760000
b100 $
b1011 "
b1011 '
b100 !
b100 )
b0 #
b0 (
b10110000 &
b10110000 %
#1770000
b1 #
b1 (
b10110001 &
b10110001 %
#1780000
b10 #
b10 (
b10110010 &
b10110010 %
#1790000
b11 #
b11 (
b10110011 &
b10110011 %
#1800000
b100 #
b100 (
b10110100 &
b10110100 %
#1810000
b101 #
b101 (
b10110101 &
b10110101 %
#1820000
b110 #
b110 (
b10110110 &
b10110110 %
#1830000
b111 #
b111 (
b10110111 &
b10110111 %
#1840000
b1000 #
b1000 (
b10111000 &
b10111000 %
#1850000
b1001 #
b1001 (
b10111001 &
b10111001 %
#1860000
b1010 #
b1010 (
b10111010 &
b10111010 %
#1870000
b10 $
b10 !
b10 )
b1011 #
b1011 (
b10111011 &
b10111011 %
#1880000
b1 $
b1 !
b1 )
b1100 #
b1100 (
b10111100 &
b10111100 %
#1890000
b1101 #
b1101 (
b10111101 &
b10111101 %
#1900000
b1110 #
b1110 (
b10111110 &
b10111110 %
#1910000
b1111 #
b1111 (
b10111111 &
b10111111 %
#1920000
b100 $
b1100 "
b1100 '
b100 !
b100 )
b0 #
b0 (
b11000000 &
b11000000 %
#1930000
b1 #
b1 (
b11000001 &
b11000001 %
#1940000
b10 #
b10 (
b11000010 &
b11000010 %
#1950000
b11 #
b11 (
b11000011 &
b11000011 %
#1960000
b100 #
b100 (
b11000100 &
b11000100 %
#1970000
b101 #
b101 (
b11000101 &
b11000101 %
#1980000
b110 #
b110 (
b11000110 &
b11000110 %
#1990000
b111 #
b111 (
b11000111 &
b11000111 %
#2000000
b1000 #
b1000 (
b11001000 &
b11001000 %
#2010000
b1001 #
b1001 (
b11001001 &
b11001001 %
#2020000
b1010 #
b1010 (
b11001010 &
b11001010 %
#2030000
b1011 #
b1011 (
b11001011 &
b11001011 %
#2040000
b10 $
b10 !
b10 )
b1100 #
b1100 (
b11001100 &
b11001100 %
#2050000
b1 $
b1 !
b1 )
b1101 #
b1101 (
b11001101 &
b11001101 %
#2060000
b1110 #
b1110 (
b11001110 &
b11001110 %
#2070000
b1111 #
b1111 (
b11001111 &
b11001111 %
#2080000
b100 $
b1101 "
b1101 '
b100 !
b100 )
b0 #
b0 (
b11010000 &
b11010000 %
#2090000
b1 #
b1 (
b11010001 &
b11010001 %
#2100000
b10 #
b10 (
b11010010 &
b11010010 %
#2110000
b11 #
b11 (
b11010011 &
b11010011 %
#2120000
b100 #
b100 (
b11010100 &
b11010100 %
#2130000
b101 #
b101 (
b11010101 &
b11010101 %
#2140000
b110 #
b110 (
b11010110 &
b11010110 %
#2150000
b111 #
b111 (
b11010111 &
b11010111 %
#2160000
b1000 #
b1000 (
b11011000 &
b11011000 %
#2170000
b1001 #
b1001 (
b11011001 &
b11011001 %
#2180000
b1010 #
b1010 (
b11011010 &
b11011010 %
#2190000
b1011 #
b1011 (
b11011011 &
b11011011 %
#2200000
b1100 #
b1100 (
b11011100 &
b11011100 %
#2210000
b10 $
b10 !
b10 )
b1101 #
b1101 (
b11011101 &
b11011101 %
#2220000
b1 $
b1 !
b1 )
b1110 #
b1110 (
b11011110 &
b11011110 %
#2230000
b1111 #
b1111 (
b11011111 &
b11011111 %
#2240000
b100 $
b1110 "
b1110 '
b100 !
b100 )
b0 #
b0 (
b11100000 &
b11100000 %
#2250000
b1 #
b1 (
b11100001 &
b11100001 %
#2260000
b10 #
b10 (
b11100010 &
b11100010 %
#2270000
b11 #
b11 (
b11100011 &
b11100011 %
#2280000
b100 #
b100 (
b11100100 &
b11100100 %
#2290000
b101 #
b101 (
b11100101 &
b11100101 %
#2300000
b110 #
b110 (
b11100110 &
b11100110 %
#2310000
b111 #
b111 (
b11100111 &
b11100111 %
#2320000
b1000 #
b1000 (
b11101000 &
b11101000 %
#2330000
b1001 #
b1001 (
b11101001 &
b11101001 %
#2340000
b1010 #
b1010 (
b11101010 &
b11101010 %
#2350000
b1011 #
b1011 (
b11101011 &
b11101011 %
#2360000
b1100 #
b1100 (
b11101100 &
b11101100 %
#2370000
b1101 #
b1101 (
b11101101 &
b11101101 %
#2380000
b10 $
b10 !
b10 )
b1110 #
b1110 (
b11101110 &
b11101110 %
#2390000
b1 $
b1 !
b1 )
b1111 #
b1111 (
b11101111 &
b11101111 %
#2400000
b100 $
b1111 "
b1111 '
b100 !
b100 )
b0 #
b0 (
b11110000 &
b11110000 %
#2410000
b1 #
b1 (
b11110001 &
b11110001 %
#2420000
b10 #
b10 (
b11110010 &
b11110010 %
#2430000
b11 #
b11 (
b11110011 &
b11110011 %
#2440000
b100 #
b100 (
b11110100 &
b11110100 %
#2450000
b101 #
b101 (
b11110101 &
b11110101 %
#2460000
b110 #
b110 (
b11110110 &
b11110110 %
#2470000
b111 #
b111 (
b11110111 &
b11110111 %
#2480000
b1000 #
b1000 (
b11111000 &
b11111000 %
#2490000
b1001 #
b1001 (
b11111001 &
b11111001 %
#2500000
b1010 #
b1010 (
b11111010 &
b11111010 %
#2510000
b1011 #
b1011 (
b11111011 &
b11111011 %
#2520000
b1100 #
b1100 (
b11111100 &
b11111100 %
#2530000
b1101 #
b1101 (
b11111101 &
b11111101 %
#2540000
b1110 #
b1110 (
b11111110 &
b11111110 %
#2550000
b10 $
b10 !
b10 )
b1111 #
b1111 (
b11111111 &
b11111111 %
#2560000
b100000000 &
b100000000 %
